google_books_driver/__init__.py
google_books_driver/retrieve.py
hirmeos_google_books-0.0.8.dist-info/LICENSE
hirmeos_google_books-0.0.8.dist-info/METADATA
hirmeos_google_books-0.0.8.dist-info/WHEEL
hirmeos_google_books-0.0.8.dist-info/top_level.txt
hirmeos_google_books-0.0.8.dist-info/RECORD
